{"nodes": [{"id": "resources_js_components_nav_user_tsx", "label": "nav-user.tsx", "file_type": "code", "source_file": "resources/js/components/nav-user.tsx", "source_location": "L1"}, {"id": "nav_user_navuser", "label": "NavUser()", "file_type": "code", "source_file": "resources/js/components/nav-user.tsx", "source_location": "L18"}], "edges": [{"source": "resources_js_components_nav_user_tsx", "target": "react", "relation": "imports_from", "confidence": "EXTRACTED", "source_file": "resources/js/components/nav-user.tsx", "source_location": "L1", "weight": 1.0}, {"source": "resources_js_components_nav_user_tsx", "target": "lucide_react", "relation": "imports_from", "confidence": "EXTRACTED", "source_file": "resources/js/components/nav-user.tsx", "source_location": "L2", "weight": 1.0}, {"source": "resources_js_components_nav_user_tsx", "target": "dropdown_menu", "relation": "imports_from", "confidence": "EXTRACTED", "source_file": "resources/js/components/nav-user.tsx", "source_location": "L3", "weight": 1.0}, {"source": "resources_js_components_nav_user_tsx", "target": "sidebar", "relation": "imports_from", "confidence": "EXTRACTED", "source_file": "resources/js/components/nav-user.tsx", "source_location": "L8", "weight": 1.0}, {"source": "resources_js_components_nav_user_tsx", "target": "user_info", "relation": "imports_from", "confidence": "EXTRACTED", "source_file": "resources/js/components/nav-user.tsx", "source_location": "L14", "weight": 1.0}, {"source": "resources_js_components_nav_user_tsx", "target": "user_menu_content", "relation": "imports_from", "confidence": "EXTRACTED", "source_file": "resources/js/components/nav-user.tsx", "source_location": "L15", "weight": 1.0}, {"source": "resources_js_components_nav_user_tsx", "target": "use_mobile", "relation": "imports_from", "confidence": "EXTRACTED", "source_file": "resources/js/components/nav-user.tsx", "source_location": "L16", "weight": 1.0}, {"source": "resources_js_components_nav_user_tsx", "target": "nav_user_navuser", "relation": "contains", "confidence": "EXTRACTED", "source_file": "resources/js/components/nav-user.tsx", "source_location": "L18", "weight": 1.0}]}